allyson/__init__.py
allyson/agent.py
allyson/agent_loop.py
allyson/browser.py
allyson/cli.py
allyson/dom_extractor.py
allyson/element.py
allyson/page.py
allyson/tools.py
allyson-0.1.6.dist-info/LICENSE
allyson-0.1.6.dist-info/METADATA
allyson-0.1.6.dist-info/WHEEL
allyson-0.1.6.dist-info/entry_points.txt
allyson-0.1.6.dist-info/top_level.txt
allyson-0.1.6.dist-info/RECORD
