Metadata-Version: 2.2
Name: allyson
Version: 0.1.6
Summary: AI-powered web browser automation
Home-page: https://github.com/Allyson-AI/python-sdk
Author: Allyson Team
Author-email: info@allyson.ai
Classifier: Development Status :: 3 - Alpha
Classifier: Intended Audience :: Developers
Classifier: License :: OSI Approved :: MIT License
Classifier: Programming Language :: Python :: 3
Classifier: Programming Language :: Python :: 3.8
Classifier: Programming Language :: Python :: 3.9
Classifier: Programming Language :: Python :: 3.10
Classifier: Programming Language :: Python :: 3.11
Requires-Python: >=3.8
License-File: LICENSE
Requires-Dist: playwright>=1.40.0
Requires-Dist: pytest-playwright>=0.4.0
Requires-Dist: tqdm>=4.66.0
Requires-Dist: pydantic>=2.0.0
Requires-Dist: pytest-asyncio>=0.21.0
Requires-Dist: pillow>=10.0.0
Provides-Extra: dev
Requires-Dist: black; extra == "dev"
Requires-Dist: isort; extra == "dev"
Requires-Dist: flake8; extra == "dev"
Requires-Dist: pytest; extra == "dev"
Requires-Dist: mypy; extra == "dev"
Dynamic: author
Dynamic: author-email
Dynamic: classifier
Dynamic: description
Dynamic: description-content-type
Dynamic: home-page
Dynamic: provides-extra
Dynamic: requires-dist
Dynamic: requires-python
Dynamic: summary
